LICENSE
MANIFEST.in
WAIVER
WARRANTY
setup.cfg
setup.py
urlybird/host.py
urlybird/merge.py
urlybird.egg-info/PKG-INFO
urlybird.egg-info/SOURCES.txt
urlybird.egg-info/dependency_links.txt
urlybird.egg-info/top_level.txt