Metadata-Version: 2.1
Name: urlybird
Version: 0.0.2
Summary: Common url operations not covered by the standard library urllib
Home-page: https://gitlab.com/chaintools/chainlib
Author: Louis Holbrook
Author-email: dev@holbrook.no
License: WTFPL
Keywords: url,internet
Platform: UNKNOWN
Classifier: Programming Language :: Python :: 3
Classifier: Operating System :: OS Independent
Classifier: Development Status :: 3 - Alpha
Classifier: Topic :: Software Development :: Libraries
Classifier: Environment :: Console
Classifier: Intended Audience :: Developers
Classifier: License :: Public Domain
Classifier: Topic :: Internet
Requires-Python: >=3.6
License-File: LICENSE
